{"cameraMode":{"drawMode":0,"name":"Shaded","section":"Shading Mode"},"sceneLighting":true,"audioPlay":false,"sceneViewState":{"m_AlwaysRefresh":false,"showFog":true,"showSkybox":true,"showFlares":true,"showImageEffects":true,"showParticleSystems":true,"showVisualEffectGraphs":true,"m_FxEnabled":true},"in2DMode":false,"pivot":{"x":8.046518325805664,"y":17.938182830810548,"z":9.78246021270752},"rotation":{"x":0.0459628701210022,"y":0.8497371077537537,"z":-0.5198066234588623,"w":0.07513966411352158},"size":0.8660253882408142,"orthographic":false}